<?xml version="1" encoding="utf-8"?>
<config>
	<game ver="0.3.3" code_size="56475648" so="libUE4.so" crc="0x9bbb4b4b">
		<file name="mrpcs.data" gray="100" a="0052E7DB" b="00000000"/>
	</game>
	<game ver="0.4.0" code_size="63023660" so="libUE4.so" crc="0xa132d7cf">
		<file name="mrpcs.data" gray="100" a="8BE10054" b="00000000"/>
	</game>
	<game ver="0.5.0" code_size="58363904" so="libUE4.so" crc="0x68fa43b1">
		<file name="mrpcs.data" gray="100" a="E004FAFC" b="2680B2E2"/>
	</game>
	<game ver="0.6.0" code_size="59359232" so="libUE4.so" crc="0x1963000c">
		<file name="mrpcs.data" gray="100" a="33BFCA02" b="02B9AB61"/>
	</game>
	<game ver="0.7.1" code_size="60043264" so="libUE4.so" crc="0xf42fd1a8">
		<file name="mrpcs.data" gray="100" a="FF926E7A" b="00000000"/>
	</game>
	<game ver="0.8.0" code_size="68143660" so="libUE4.so" crc="0xd815ee98">
		<file name="mrpcs.data" gray="100" a="16FD427A" b="831C741F"/>
	</game>
	<game ver="0.8.3" code_size="68143660" so="libUE4.so" crc="0xed50e4d5">
		<file name="mrpcs.data" gray="100" a="C0316D89" b="44D2D1E9"/>
	</game>
	<game ver="0.8.4" code_size="68143660" so="libUE4.so" crc="0xf10cc518">
		<file name="mrpcs.data" gray="100" a="0C0D753B" b="00000000"/>
	</game>
	<game ver="0.9.0" code_size="78993964" so="libUE4.so" crc="0xfd011520">
		<file name="mrpcs.data" gray="100" a="EF2C4E38" b="AF44640E"/>
	</game>
	<game ver="0.10.0" code_size="77089324" so="libUE4.so" crc="0xa22b6641">
		<file name="mrpcs.data" gray="100" a="F555CAFC" b="94027011"/>
	</game>
	<game ver="0.11.0" code_size="82438700" so="libUE4.so" crc="0x39279d14">
		<file name="mrpcs.data" gray="100" a="2360C222" b="BBA47B46"/>
	</game>
	<game ver="0.11.1" code_size="82438700" so="libUE4.so" crc="0xd63059f3">
		<file name="mrpcs.data" gray="100" a="CF82FD8D" b="4C58D252"/>
	</game>
	<game ver="0.11.2" code_size="82438700" so="libUE4.so" crc="0xe6a8d605">
		<file name="mrpcs.data" gray="100" a="A4AB7906" b="D223E168"/>
	</game>
	<game ver="0.12.0" code_size="84544044" so="libUE4.so" crc="0xe75bae3a">
		<file name="mrpcs.data" gray="100" a="776CD7DB" b="4AE589EE"/>
	</game>
	<game ver="0.12.1" code_size="84560428" so="libUE4.so" crc="0xc0ea98a6">
		<file name="mrpcs.data" gray="100" a="BF19F0FD" b="00000000"/>
	</game>
	<game ver="0.13.0" code_size="86428204" so="libUE4.so" crc="0xfb5f020a">
		<file name="mrpcs.data" gray="100" a="8321ACBC" b="80619B22"/>
	</game>
	<game ver="0.13.1" code_size="86415916" so="libUE4.so" crc="0xe0e4e038">
		<file name="mrpcs.data" gray="100" a="8321ACBC" b="80619B22"/>
	</game>
	<game ver="0.14.0" code_size="88545836" so="libUE4.so" crc="0xe6dcae3d">
		<file name="mrpcs.data" gray="100" a="32793010" b="E7D140F3"/>
	</game>
	<game ver="0.14.1" code_size="88570412" so="libUE4.so" crc="0xa34225e5">
		<file name="mrpcs.data" gray="100" a="ABD2C588" b="00000000"/>
	</game>
	<game ver="0.15.0" code_size="91757100" so="libUE4.so" crc="0x3f13b81c">
		<file name="mrpcs.data" gray="100" a="31CEE942" b="171200DC"/>
	</game>
	<game ver="0.15.1" code_size="91769388" so="libUE4.so" crc="0xb16a4b1c">
		<file name="mrpcs.data" gray="100" a="2EB59BD0" b="00000000"/>
	</game>
	<game ver="0.16.0" code_size="96729644" so="libUE4.so" crc="0xda3779df">
		<file name="mrpcs.data" gray="100" a="6970A34A" b="6E13238C"/>
	</game>
	<game ver="0.16.1" code_size="96733740" so="libUE4.so" crc="0xe58c54b4">
		<file name="mrpcs.data" gray="100" a="84C64194" b="00000000"/>
	</game>
	<game ver="0.17.0" code_size="100141612" so="libUE4.so" crc="0xf0c731e1">
		<file name="mrpcs.data" gray="100" a="1D77910D" b="41F6B10D"/>
	</game>
	<game ver="0.17.1" code_size="100145708" so="libUE4.so" crc="0x9d6b14b7">
		<file name="mrpcs.data" gray="100" a="3A6A0342" b="647AABDA"/>
	</game>
	<game ver="0.18.0" code_size="103737900" so="libUE4.so" crc="0x9a68b062">
		<file name="mrpcs.data" gray="100" a="F1DF58D2" b="FD2E2012"/>
	</game>
	<game ver="0.19.0" code_size="106510900" so="libUE4.so" crc="0xdee05fc1">
		<file name="mrpcs.data" gray="100" a="B89853F1" b="E6238B27"/>
	</game>
	<game ver="0.19.5" code_size="144259864" so="libUE4.so" crc="0x3681fa8b">
		<file name="mrpcs.data" gray="100" a="F25CFB84" b="00000000"/>
	</game>
	<game ver="0.19.1" code_size="105982508" so="libUE4.so" crc="0xa9f7cee0">
		<file name="mrpcs.data" gray="100" a="BCEF27DF" b="00000000"/>
	</game>
	<game ver="0.19.6" code_size="144325400" so="libUE4.so" crc="0x41fb0000">
		<file name="mrpcs.data" gray="100" a="F4E9364A" b="00000000"/>
	</game>
	<game ver="0.19.2" code_size="106564148" so="libUE4.so" crc="0xfa19bb82">
		<file name="mrpcs.data" gray="100" a="13B16BDF" b="00000000"/>
	</game>
	<game ver="1.0.5" code_size="148781848" so="libUE4.so" crc="0xc90b87db">
		<file name="mrpcs.data" gray="100" a="B955FC60" b="EA8F123A"/>
	</game>
	<game ver="1.0.0" code_size="109640244" so="libUE4.so" crc="0x8f5ccb9c">
		<file name="mrpcs.data" gray="100" a="A3656E17" b="C04F257A"/>
	</game>
	<game ver="1.0.1" code_size="109111852" so="libUE4.so" crc="0xec9b6d84">
		<file name="mrpcs.data" gray="100" a="2D2E3ABC" b="00000000"/>
	</game>
	<game ver="0.19.3" code_size="106592820" so="libUE4.so" crc="0x454ce3ea">
		<file name="mrpcs.data" gray="100" a="BD011716" b="00000000"/>
	</game>
	<game ver="1.0.2" code_size="109673012" so="libUE4.so" crc="0x62b984ea">
		<file name="mrpcs.data" gray="100" a="CB463D58" b="7FED9B5A"/>
	</game>
	<game ver="1.0.3" code_size="109673012" so="libUE4.so" crc="0x1a2cd5f3">
		<file name="mrpcs.data" gray="100" a="DB2A3FB7" b="00000000"/>
	</game>
	<game ver="1.0.6" code_size="148912920" so="libUE4.so" crc="0x2aca3680">
		<file name="mrpcs.data" gray="100" a="43CD2978" b="00000000"/>
	</game>
	<game ver="1.1.0" code_size="113748532" so="libUE4.so" crc="0x69e4f725">
		<file name="mrpcs.data" gray="100" a="E0E75CE8" b="62F754EB"/>
	</game>
	<game ver="1.1.5" code_size="154614552" so="libUE4.so" crc="0x86f96c4f">
		<file name="mrpcs.data" gray="100" a="432194D7" b="633FD163"/>
	</game>
	<game ver="1.1.1" code_size="113220140" so="libUE4.so" crc="0x97e77767">
		<file name="mrpcs.data" gray="100" a="6ED4205C" b="00000000"/>
	</game>
	<game ver="1.2.0" code_size="115518004" so="libUE4.so" crc="0xf6efbd4d">
		<file name="mrpcs.data" gray="100" a="9A1C01FB" b="30B3EEFF"/>
	</game>
	<game ver="1.2.5" code_size="157039384" so="libUE4.so" crc="0x4f63e366">
		<file name="mrpcs.data" gray="100" a="6A8FA03F" b="6BE5EC6C"/>
	</game>
	<game ver="1.2.1" code_size="114989612" so="libUE4.so" crc="0x7c0a31ee">
		<file name="mrpcs.data" gray="100" a="88B06994" b="00000000"/>
	</game>
	<game ver="1.3.5" code_size="159071000" so="libUE4.so" crc="0x98e980fd">
		<file name="mrpcs.data" gray="100" a="168064B0" b="17426D19"/>
	</game>
	<game ver="1.3.0" code_size="116460084" so="libUE4.so" crc="0x541be1b5">
		<file name="mrpcs.data" gray="100" a="E8AC7584" b="772850C9"/>
	</game>
	<game ver="1.3.1" code_size="116464180" so="libUE4.so" crc="0x47b55ba2">
		<file name="mrpcs.data" gray="100" a="C5AAB8DC" b="36552710"/>
	</game>
	<game ver="1.4.0" code_size="117971508" so="libUE4.so" crc="0x914ac4f8">
		<file name="mrpcs.data" gray="100" a="1D0C9A0F" b="314DEC8E"/>
	</game>
	<game ver="1.4.5" code_size="161626904" so="libUE4.so" crc="0x6307535c">
		<file name="mrpcs.data" gray="100" a="C7A499A4" b="804D73E5"/>
	</game>
	<game ver="1.5.0" code_size="120633908" so="libUE4.so" crc="0x054da096">
		<file name="mrpcs.data" gray="100" a="15B71FAD" b="DDEF0D9C"/>
	</game>
	<game ver="1.5.5" code_size="165624600" so="libUE4.so" crc="0xc0b1f458">
		<file name="mrpcs.data" gray="100" a="FFA0BC53" b="4EDEC924"/>
	</game>
	<game ver="1.6.5" code_size="166673176" so="libUE4.so" crc="0xed2a2a10">
		<file name="mrpcs.data" gray="100" a="23D2205F" b="D4C79523"/>
	</game>
	<game ver="1.6.0" code_size="121449012" so="libUE4.so" crc="0x69129ebd">
		<file name="mrpcs.data" gray="100" a="F69E159B" b="1E3E3308"/>
	</game>
	<game ver="1.7.0" code_size="125831732" so="libUE4.so" crc="0xf14e5c55">
		<file name="mrpcs.data" gray="100" a="20D16859" b="E9BC3311"/>
	</game>
	<game ver="1.7.5" code_size="172702488" so="libUE4.so" crc="0x66da4e9e">
		<file name="mrpcs.data" gray="100" a="3639C7C4" b="EE3DDA64"/>
	</game>
	<game ver="1.8.0" code_size="123345460" so="libUE4.so" crc="0x8c6fd9ce">
		<file name="mrpcs.data" gray="100" a="58CEC268" b="8BCF276F"/>
	</game>
	<game ver="1.8.5" code_size="170474328" so="libUE4.so" crc="0x203413d7">
		<file name="mrpcs.data" gray="100" a="10865A51" b="F89E89EA"/>
	</game>
	<game ver="1.9.5" code_size="171457368" so="libUE4.so" crc="0x73fed491">
		<file name="mrpcs.data" gray="100" a="40EE63CC" b="F40A084B"/>
	</game>
	<game ver="1.9.0" code_size="124217908" so="libUE4.so" crc="0x80577306">
		<file name="mrpcs.data" gray="100" a="A6878028" b="2E5ED800"/>
	</game>
	<game ver="2.0.0" code_size="126495284" so="libUE4.so" crc="0x0575971a">
		<file name="mrpcs.data" gray="10" a="70C0EC84" b="47132C08"/>
	</game>
	<game ver="2.0.5" code_size="174537560" so="libUE4.so" crc="0x427d5a67">
		<file name="mrpcs.data" gray="100" a="7C919513" b="EEF1C1EB"/>
	</game>
	<game ver="2.1.0" code_size="125712948" so="libUE4.so" crc="0xfd84eb21">
		<file name="mrpcs.data" gray="100" a="613436E5" b="DA04A9B3"/>
	</game>
	<game ver="2.1.5" code_size="173620056" so="libUE4.so" crc="0xcf0f4542">
		<file name="mrpcs.data" gray="100" a="CF1E5578" b="03B9A77E"/>
	</game>
	<game ver="2.2.5" code_size="178891800" so="libUE4.so" crc="0x1f813744">
		<file name="mrpcs.data" gray="100" a="5E106157" b="00000000"/>
	</game>
	<game ver="2.2.0" code_size="129333812" so="libUE4.so" crc="0x62d580a8">
		<file name="mrpcs.data" gray="100" a="A14204AD" b="1B7828BC"/>
	</game>
	<game ver="2.3.5" code_size="180466792" so="libUE4.so" crc="0xf0d8f96f">
		<file name="mrpcs.data" gray="100" a="BC34EF12" b="9C4ED62C"/>
	</game>
	<game ver="2.3.0" code_size="130131192" so="libUE4.so" crc="0x515b513e">
		<file name="mrpcs.data" gray="100" a="3932091D" b="55BE0FF9"/>
	</game>
	<game ver="2.4.5" code_size="185543312" so="libUE4.so" crc="0x8a2b254f">
		<file name="mrpcs.data" gray="100" a="8DFAA8DD" b="E05B3AA6"/>
	</game>
	<game ver="2.4.0" code_size="133264080" so="libUE4.so" crc="0xf87dc013">
		<file name="mrpcs.data" gray="100" a="0DAAC1E3" b="6AD0BFE2"/>
	</game>
	<game ver="2.5.0" code_size="139638120" so="libUE4.so" crc="0xa7d74e20">
		<file name="mrpcs.data" gray="100" a="98316CDB" b="D4C562FF"/>
	</game>
	<game ver="2.5.5" code_size="192558264" so="libUE4.so" crc="0xe7351e2b">
		<file name="mrpcs.data" gray="100" a="EABB64FB" b="9052C582"/>
	</game>
	<game ver="2.6.0" code_size="141928792" so="libUE4.so" crc="0x57a46835">
		<file name="mrpcs.data" gray="100" a="DFFDC66A" b="98F33672"/>
	</game>
</config>
